jira_select/__init__.py
jira_select/__main__.py
jira_select/cache.py
jira_select/cmdline.py
jira_select/constants.py
jira_select/exceptions.py
jira_select/plugin.py
jira_select/query.py
jira_select/types.py
jira_select/utils.py
jira_select/commands/__init__.py
jira_select/commands/batch.py
jira_select/commands/build_query.py
jira_select/commands/configure.py
jira_select/commands/functions.py
jira_select/commands/install_user_script.py
jira_select/commands/remove_instance.py
jira_select/commands/run.py
jira_select/commands/run_script.py
jira_select/commands/schema.py
jira_select/commands/setup_instance.py
jira_select/commands/shell.py
jira_select/commands/show_instances.py
jira_select/commands/store_password.py
jira_select/formatters/__init__.py
jira_select/formatters/csv.py
jira_select/formatters/html.py
jira_select/formatters/json.py
jira_select/formatters/raw.py
jira_select/formatters/table.py
jira_select/formatters/tsv.py
jira_select/functions/__init__.py
jira_select/functions/estimate_to_days.py
jira_select/functions/extract.py
jira_select/functions/field_by_name.py
jira_select/functions/flatten_changelog.py
jira_select/functions/flatten_list.py
jira_select/functions/get_issue.py
jira_select/functions/get_issue_snapshot_on_date.py
jira_select/functions/get_linked_issue_keys.py
jira_select/functions/get_sprint_by_id.py
jira_select/functions/get_sprint_by_name.py
jira_select/functions/interval_business_hours.py
jira_select/functions/interval_matching.py
jira_select/functions/interval_size.py
jira_select/functions/json_dumps.py
jira_select/functions/now.py
jira_select/functions/parse_date.py
jira_select/functions/parse_datetime.py
jira_select/functions/simple_filter.py
jira_select/functions/simple_filter_any.py
jira_select/functions/sprint_details.py
jira_select/functions/sprint_name.py
jira_select/functions/subquery.py
jira_select/functions/union.py
jira_select/functions/workdays_in_state.py
jira_select/sources/__init__.py
jira_select/sources/boards.py
jira_select-3.4.2.dist-info/METADATA
jira_select-3.4.2.dist-info/WHEEL
jira_select-3.4.2.dist-info/entry_points.txt
jira_select-3.4.2.dist-info/top_level.txt
jira_select-3.4.2.dist-info/RECORD
