Metadata-Version: 2.4
Name: jira-select
Version: 3.4.2
Summary: Easily run complex SQL-like queries far beyond what Jira's standard JQL query language can provide.
Home-page: https://github.com/coddingtonbear/jira-select
Author: Adam Coddington
Author-email: me@adamcoddington.net
License: MIT
Project-URL: Issue Tracker, https://github.com/coddingtonbear/jira-select/issues
Keywords: jira,csv,sql
Classifier: Development Status :: 5 - Production/Stable
Classifier: Intended Audience :: Developers
Classifier: License :: OSI Approved :: MIT License
Classifier: Operating System :: Unix
Classifier: Operating System :: POSIX
Classifier: Operating System :: Microsoft :: Windows
Classifier: Programming Language :: Python
Classifier: Programming Language :: Python :: 3
Classifier: Programming Language :: Python :: 3.7
Classifier: Programming Language :: Python :: 3.8
Classifier: Programming Language :: Python :: 3.9
Classifier: Development Status :: 4 - Beta
Classifier: Environment :: Console
Classifier: Programming Language :: Python :: 3
Classifier: Topic :: Utilities
Requires-Python: >=3.6
Requires-Dist: rich<14.0,>=13.3.2
Requires-Dist: appdirs<2.0.0,>=1.4.4
Requires-Dist: keyring<23.0.0,>=21.2.1
Requires-Dist: jira<4.0,>=3.10.5
Requires-Dist: python-dateutil<3.0.0,>=2.8.1
Requires-Dist: pyyaml<7,>=6.0.2
Requires-Dist: simpleeval<1.0,>=0.9.13
Requires-Dist: prompt-toolkit<4.0.0,>=3.0.5
Requires-Dist: dotmap<2.0.0,>=1.3.17
Requires-Dist: typing_extensions<5.0,>=4.2
Requires-Dist: visidata>=1.0.0
Requires-Dist: pygments<3.0.0,>=2.6.1
Requires-Dist: diskcache<5.0.0,>=4.1.0
Requires-Dist: queryablelist<4.0.0,>=3.1.0
Requires-Dist: pytz
Requires-Dist: safdie<3.0,>=2.0.4
Requires-Dist: pydantic<3.0,>=2.11.0
Requires-Dist: portion<3.0,>=2.4.0
Dynamic: author
Dynamic: author-email
Dynamic: classifier
Dynamic: description
Dynamic: description-content-type
Dynamic: home-page
Dynamic: keywords
Dynamic: license
Dynamic: project-url
Dynamic: requires-dist
Dynamic: requires-python
Dynamic: summary
